setup.cfg
setup.py
icyparser/__init__.py
icyparser/icyparser.py
icyparser.egg-info/PKG-INFO
icyparser.egg-info/SOURCES.txt
icyparser.egg-info/dependency_links.txt
icyparser.egg-info/top_level.txt