Metadata-Version: 1.0
Name: icyparser
Version: 1.1.2
Summary: A script to download the ICY information for a stream and return it as a dict
Home-page: https://github.com/GijsTimmers/icyparser
Author: Gijs Timmers
Author-email: gijs.timmers@student.kuleuven.be
License: UNKNOWN
Keywords: shoutcast,icecast,stream,ICY
Platform: UNKNOWN
